README.txt
setup.py
rjm/__init__.py
rjm.recipe.venv.egg-info/PKG-INFO
rjm.recipe.venv.egg-info/SOURCES.txt
rjm.recipe.venv.egg-info/dependency_links.txt
rjm.recipe.venv.egg-info/entry_points.txt
rjm.recipe.venv.egg-info/namespace_packages.txt
rjm.recipe.venv.egg-info/not-zip-safe
rjm.recipe.venv.egg-info/requires.txt
rjm.recipe.venv.egg-info/top_level.txt
rjm/recipe/__init__.py
rjm/recipe/venv/__init__.py