Metadata-Version: 1.0
Name: rjm.recipe.venv
Version: 0.8
Summary: zc.buildout recipe to turn the entire buildout tree into a virtualenv
Home-page: http://www.bitbucket.org/rafrombrc/rjm.recipe.venv
Author: Rob Miller
Author-email: rob@kalistra.com
License: MIT
Keywords: buildout virtualenv
Platform: UNKNOWN
Classifier: Framework :: Buildout
Classifier: Intended Audience :: Developers
Classifier: Topic :: Software Development :: Build Tools
Classifier: Topic :: Software Development :: Libraries :: Python Modules
Classifier: License :: OSI Approved :: MIT License
